[
    { "MapName": "トウカシティ", "Seed": "622B124D", "Name": "トサキント", "Lv": 10, "PID": "1F0C75C9", "Nature": "すなお", "IVs": [ 6, 18, 11, 12, 21, 25 ] },
    { "MapName": "トウカシティ", "Seed": "D4787195", "Name": "コイキング", "Lv": 5, "PID": "22A986FC", "Nature": "のうてんき", "IVs": [ 26, 4, 16, 8, 11, 5 ] },
    { "MapName": "トウカシティ", "Seed": "AB18EAF6", "Name": "コイキング", "Lv": 7, "PID": "0077EB1C", "Nature": "なまいき", "IVs": [ 17, 21, 0, 10, 21, 30 ] },
    { "MapName": "119ばんどうろ", "Seed": "FC170FFD", "Name": "コイキング", "Lv": 9, "PID": "52009AEC", "Nature": "なまいき", "IVs": [ 23, 23, 18, 10, 15, 7 ] },
    { "MapName": "119ばんどうろ", "Seed": "D4BD10AB", "Name": "メノクラゲ", "Lv": 5, "PID": "155CDC99", "Nature": "おとなしい", "IVs": [ 23, 31, 16, 18, 28, 28 ] },
    { "MapName": "119ばんどうろ", "Seed": "2039BD5B", "Name": "コイキング", "Lv": 8, "PID": "D8505BA9", "Nature": "さみしがり", "IVs": [ 1, 16, 31, 19, 26, 23 ] },
    { "MapName": "119ばんどうろ(ヒンバススポット)", "Seed": "E6C45BB9", "Name": "ヒンバス", "Lv": 21, "PID": "47311291", "Nature": "いじっぱり", "IVs": [ 17, 7, 24, 29, 22, 5 ] },
    { "MapName": "119ばんどうろ(ヒンバススポット)", "Seed": "8A132986", "Name": "コイキング", "Lv": 6, "PID": "F6A0353A", "Nature": "なまいき", "IVs": [ 20, 5, 23, 21, 3, 12 ] },
    { "MapName": "119ばんどうろ(ヒンバススポット)", "Seed": "6C01E733", "Name": "ヒンバス", "Lv": 22, "PID": "CC90B9A5", "Nature": "しんちょう", "IVs": [ 5, 0, 6, 28, 10, 1 ] },
    { "MapName": "119ばんどうろ(ヒンバススポット)", "Seed": "46D031DA", "Name": "コイキング", "Lv": 9, "PID": "B40B933F", "Nature": "おとなしい", "IVs": [ 2, 6, 6, 8, 5, 28 ] },
    { "MapName": "119ばんどうろ(ヒンバススポット)", "Seed": "5925D991", "Name": "ヒンバス", "Lv": 21, "PID": "89EF6804", "Nature": "きまぐれ", "IVs": [ 18, 21, 19, 24, 22, 5 ] },
    { "MapName": "サファリゾーン 追加エリア", "Seed": "07B3536C", "Name": "トサキント", "Lv": 25, "PID": "E46DC464", "Nature": "しんちょう", "IVs": [ 29, 24, 16, 29, 20, 5 ] },
    { "MapName": "サファリゾーン 追加エリア", "Seed": "D02DE544", "Name": "コイキング", "Lv": 25, "PID": "20304514", "Nature": "きまぐれ", "IVs": [ 30, 26, 7, 10, 16, 27 ] },
    { "MapName": "サファリゾーン 追加エリア", "Seed": "E0595588", "Name": "トサキント", "Lv": 29, "PID": "F3491567", "Nature": "おだやか", "IVs": [ 15, 28, 6, 26, 7, 3 ] },
    { "MapName": "サファリゾーン 追加エリア", "Seed": "C720180C", "Name": "コイキング", "Lv": 28, "PID": "4E517390", "Nature": "しんちょう", "IVs": [ 26, 28, 26, 23, 27, 19 ] },
    { "MapName": "サファリゾーン 追加エリア", "Seed": "E36A684A", "Name": "コイキング", "Lv": 30, "PID": "E7E7AA31", "Nature": "すなお", "IVs": [ 4, 25, 10, 25, 24, 5 ] },
    { "MapName": "サファリゾーン 追加エリア", "PokeBlock": "あか", "Seed": "3E629B4E", "Name": "コイキング", "Lv": 28, "PID": "64C404DF", "Nature": "いじっぱり", "IVs": [ 18, 12, 23, 29, 23, 4 ] },
    { "MapName": "サファリゾーン 追加エリア", "PokeBlock": "あか", "Seed": "1FECCA3B", "Name": "コイキング", "Lv": 27, "PID": "AEC41C31", "Nature": "のんき", "IVs": [ 15, 19, 16, 23, 3, 1 ] },
    { "MapName": "サファリゾーン 追加エリア", "PokeBlock": "あか", "Seed": "FF80E843", "Name": "コイキング", "Lv": 27, "PID": "0538CC1F", "Nature": "さみしがり", "IVs": [ 16, 15, 16, 24, 26, 15 ] },
    { "MapName": "サファリゾーン 追加エリア", "PokeBlock": "あか", "Seed": "1E53A5CA", "Name": "トサキント", "Lv": 25, "PID": "D92F46C0", "Nature": "さみしがり", "IVs": [ 30, 25, 31, 6, 14, 1 ] },    
    { "MapName": "サファリゾーン 追加エリア", "PokeBlock": "あか", "Seed": "0A4D9143", "Name": "コイキング", "Lv": 28, "PID": "7EA59F12", "Nature": "いじっぱり", "IVs": [ 30, 11, 21, 1, 4, 27 ] }
]